sumfolder1/__init__.py
sumfolder1/droidcsvhandler.py
sumfolder1/referenceset.py
sumfolder1/results.py
sumfolder1/storageobjects.py
sumfolder1/sumfolder1.py
sumfolder1/sumfolders.py
sumfolder1/utilities.py
sumfolder1/version.py
sumfolder1-0.0.2.dist-info/LICENSE
sumfolder1-0.0.2.dist-info/METADATA
sumfolder1-0.0.2.dist-info/WHEEL
sumfolder1-0.0.2.dist-info/entry_points.txt
sumfolder1-0.0.2.dist-info/top_level.txt
sumfolder1-0.0.2.dist-info/RECORD
