Metadata-Version: 2.1
Name: sumfolder1
Version: 0.0.2
Summary: Checksums for folders.
Home-page: https://github.com/ross-spencer/sumfolder1
Author: Ross Spencer
Author-email: all.along.the.watchtower2001+github@gmail.com
License: UNKNOWN
Project-URL: Bug Reports, https://github.com/ross-spencer/sumfolder1/issues
Project-URL: Source, https://github.com/ross-spencer/sumfolder1
Keywords: digital-preservation,collection-analysis,checksums,merkle-tree
Platform: UNKNOWN
Classifier: Development Status :: 4 - Beta
Classifier: Intended Audience :: Developers
Classifier: Intended Audience :: Information Technology
Classifier: Intended Audience :: Other Audience
Classifier: Topic :: System :: Archiving
Classifier: License :: OSI Approved :: GNU General Public License v3 (GPLv3)
Classifier: Programming Language :: Python :: 3
Requires-Python: >=3.9, <4
License-File: LICENSE
Requires-Dist: colorama (==0.4.6)
